astroinsight/__init__.py
astroinsight/cli.py
astroinsight/mcp_server.py
astroinsight-0.1.1.dist-info/METADATA
astroinsight-0.1.1.dist-info/WHEEL
astroinsight-0.1.1.dist-info/entry_points.txt
astroinsight-0.1.1.dist-info/top_level.txt
astroinsight-0.1.1.dist-info/RECORD
