Metadata-Version: 2.4
Name: astroinsight
Version: 0.1.1
Summary: AI-powered research paper assistant with multi-agent collaboration
Home-page: https://github.com/yourusername/astroinsight
Author: AstroInsight Team
Author-email: AstroInsight Team <contact@astroinsight.com>
Maintainer-email: AstroInsight Team <contact@astroinsight.com>
License-Expression: MIT
Project-URL: Homepage, https://github.com/yourusername/astroinsight
Project-URL: Documentation, https://astroinsight.readthedocs.io/
Project-URL: Repository, https://github.com/yourusername/astroinsight
Project-URL: Bug Tracker, https://github.com/yourusername/astroinsight/issues
Keywords: ai,research,paper,multi-agent,collaboration,astroinsight
Classifier: Development Status :: 3 - Alpha
Classifier: Intended Audience :: Science/Research
Classifier: Operating System :: OS Independent
Classifier: Programming Language :: Python :: 3
Classifier: Programming Language :: Python :: 3.8
Classifier: Programming Language :: Python :: 3.9
Classifier: Programming Language :: Python :: 3.10
Classifier: Programming Language :: Python :: 3.11
Classifier: Topic :: Scientific/Engineering :: Artificial Intelligence
Classifier: Topic :: Scientific/Engineering :: Information Analysis
Requires-Python: >=3.8
Requires-Dist: click>=8.0.0
Requires-Dist: requests>=2.25.0
Requires-Dist: openpyxl>=3.0.0
Requires-Dist: python-dotenv>=1.0.0
Provides-Extra: dev
Requires-Dist: pytest>=7.0.0; extra == "dev"
Requires-Dist: black>=24.10.0; extra == "dev"
Requires-Dist: flake8>=7.1.1; extra == "dev"
Requires-Dist: mypy>=1.0.0; extra == "dev"
Requires-Dist: twine>=4.0.0; extra == "dev"
Requires-Dist: wheel>=0.40.0; extra == "dev"
Provides-Extra: mcp
Requires-Dist: mcp>=1.0.0; extra == "mcp"
Requires-Dist: asyncio-mqtt>=0.16.0; extra == "mcp"
Requires-Dist: aiohttp>=3.8.0; extra == "mcp"
Requires-Dist: websockets>=11.0.0; extra == "mcp"
Provides-Extra: full
Requires-Dist: mcp>=1.0.0; extra == "full"
Requires-Dist: asyncio-mqtt>=0.16.0; extra == "full"
Requires-Dist: aiohttp>=3.8.0; extra == "full"
Requires-Dist: websockets>=11.0.0; extra == "full"
Requires-Dist: pytest>=7.0.0; extra == "full"
Requires-Dist: black>=24.10.0; extra == "full"
Requires-Dist: flake8>=7.1.1; extra == "full"
Requires-Dist: mypy>=1.0.0; extra == "full"
Dynamic: author
Dynamic: home-page
Dynamic: requires-python
